exc2issue/__init__.py
exc2issue/adapters/_base_ai_client.py
exc2issue/adapters/gemini/__init__.py
exc2issue/adapters/gemini/_fallback.py
exc2issue/adapters/gemini/_format_functions.py
exc2issue/adapters/gemini/_prompt_builder.py
exc2issue/adapters/gemini/client.py
exc2issue/adapters/github/__init__.py
exc2issue/adapters/github/_api_utils.py
exc2issue/adapters/github/_app_auth.py
exc2issue/adapters/github/_auth_manager.py
exc2issue/adapters/github/_formatters_base.py
exc2issue/adapters/github/_formatters_common.py
exc2issue/adapters/github/_formatters_single.py
exc2issue/adapters/github/_formatters_summary.py
exc2issue/adapters/github/_formatters_timeline.py
exc2issue/adapters/github/_issue_creation.py
exc2issue/adapters/github/_issue_formatting.py
exc2issue/adapters/github/_sanitization.py
exc2issue/adapters/github/_search.py
exc2issue/adapters/github/_url_validation.py
exc2issue/adapters/github/_validation.py
exc2issue/adapters/github/client.py
exc2issue/adapters/vertexai/__init__.py
exc2issue/adapters/vertexai/client.py
exc2issue/config/__init__.py
exc2issue/config/_base.py
exc2issue/config/github.py
exc2issue/config/google_ai.py
exc2issue/config/logging.py
exc2issue/core/__init__.py
exc2issue/core/background_worker.py
exc2issue/core/client_factory.py
exc2issue/core/config_types.py
exc2issue/core/decorator.py
exc2issue/core/error_collection.py
exc2issue/core/error_handling.py
exc2issue/core/handlers.py
exc2issue/core/issue_creator.py
exc2issue/core/models.py
exc2issue/core/registry.py
exc2issue/core/signal_handling.py
exc2issue/core/task_queue.py
exc2issue/core/task_types.py
exc2issue/core/utils.py
exc2issue/decorator.py
exc2issue/observability/__init__.py
exc2issue/observability/metrics_collector.py
exc2issue/py.typed
exc2issue/types.py
exc2issue-0.7.0.dist-info/WHEEL
exc2issue-0.7.0.dist-info/METADATA
exc2issue-0.7.0.dist-info/RECORD
