Metadata-Version: 2.3
Name: exc2issue
Version: 0.7.0
Summary: A Python decorator that automatically creates GitHub issues when functions encounter errors or log critical messages
Author: DucretJe
Author-email: DucretJe <github@ducret.mozmail.com>
Requires-Dist: build>=1.3.0
Requires-Dist: cryptography>=44.0.0
Requires-Dist: google-genai>=1.36.0
Requires-Dist: pydantic>=2.11.9
Requires-Dist: pydantic-settings>=2.10.1
Requires-Dist: pyjwt>=2.10.1
Requires-Dist: requests>=2.32.5
Requires-Dist: google-genai>=1.36.0 ; extra == 'ai'
Requires-Python: >=3.12
Provides-Extra: ai
